{
 "1997": {
  "Alabama": "",
  "Alaska": "",
  "Arizona": "",
  "Arkansas": "",
  "California": "",
  "Colorado": "",
  "Connecticut": "",
  "Delaware": "",
  "District of Columbia": "",
  "Florida": "",
  "Georgia": "",
  "Hawaii": "",
  "Idaho": "",
  "Illinois": "",
  "Indiana": "",
  "Iowa": "",
  "Kansas": "",
  "Kentucky": "",
  "Louisiana": "",
  "Maine": "",
  "Maryland": "",
  "Massachusetts": "",
  "Michigan": "",
  "Minnesota": "",
  "Mississippi": "",
  "Missouri": "",
  "Montana": "",
  "Nebraska": "",
  "Nevada": "",
  "New Hampshire": "",
  "New Jersey": "",
  "New Mexico": "",
  "New York": "",
  "North Carolina": "",
  "North Dakota": "",
  "Ohio": "",
  "Oklahoma": "",
  "Oregon": "",
  "Pennsylvania": "",
  "Rhode Island": "",
  "South Carolina": "",
  "South Dakota": "",
  "Tennessee": "",
  "Texas": "",
  "Utah": "",
  "Vermont": "",
  "Virginia": "",
  "Washington": "",
  "West Virginia": "",
  "Wisconsin": "",
  "Wyoming": ""
 },
 "1998": {
  "Alabama": "466612",
  "Alaska": "191552",
  "Arizona": "1056011",
  "Arkansas": "747505",
  "California": "6728104",
  "Colorado": "575345",
  "Connecticut": "566277",
  "Delaware": "173864",
  "District of Columbia": "236155",
  "Florida": "2136110",
  "Georgia": "1379270",
  "Hawaii": "188087",
  "Idaho": "134826",
  "Illinois": "2351632",
  "Indiana": "751832",
  "Iowa": "484715",
  "Kansas": "340839",
  "Kentucky": "980372",
  "Louisiana": "1182984",
  "Maine": "356216",
  "Maryland": "922667",
  "Massachusetts": "1346901",
  "Michigan": "1569626",
  "Minnesota": "967362",
  "Mississippi": "595463",
  "Missouri": "994307",
  "Montana": "138134",
  "Nebraska": "294115",
  "Nevada": "257616",
  "New Hampshire": "221428",
  "New Jersey": "1440474",
  "New Mexico": "634510",
  "New York": "6695326",
  "North Carolina": "1726447",
  "North Dakota": "81011",
  "Ohio": "1818473",
  "Oklahoma": "556707",
  "Oregon": "660504",
  "Pennsylvania": "3033803",
  "Rhode Island": "233951",
  "South Carolina": "751477",
  "South Dakota": "139311",
  "Tennessee": "1166677",
  "Texas": "3941273",
  "Utah": "300539",
  "Vermont": "140101",
  "Virginia": "795598",
  "Washington": "1099718",
  "West Virginia": "394508",
  "Wisconsin": "833744",
  "Wyoming": "68962"
 },
 "1999": {
  "Alabama": "582231",
  "Alaska": "219466",
  "Arizona": "1093281",
  "Arkansas": "707473",
  "California": "7437021",
  "Colorado": "666726",
  "Connecticut": "574005",
  "Delaware": "200086",
  "District of Columbia": "308501",
  "Florida": "2493379",
  "Georgia": "1529435",
  "Hawaii": "242188",
  "Idaho": "188107",
  "Illinois": "2046381",
  "Indiana": "903911",
  "Iowa": "462343",
  "Kansas": "351559",
  "Kentucky": "1018305",
  "Louisiana": "997323",
  "Maine": "469212",
  "Maryland": "1144752",
  "Massachusetts": "1360346",
  "Michigan": "1458310",
  "Minnesota": "964894",
  "Mississippi": "630702",
  "Missouri": "1075913",
  "Montana": "125414",
  "Nebraska": "328815",
  "Nevada": "246049",
  "New Hampshire": "257683",
  "New Jersey": "1579961",
  "New Mexico": "584160",
  "New York": "7170232",
  "North Carolina": "1709352",
  "North Dakota": "81337",
  "Ohio": "1730651",
  "Oklahoma": "567959",
  "Oregon": "775667",
  "Pennsylvania": "3537178",
  "Rhode Island": "267227",
  "South Carolina": "766300",
  "South Dakota": "133550",
  "Tennessee": "1460180",
  "Texas": "4339926",
  "Utah": "245623",
  "Vermont": "175795",
  "Virginia": "792614",
  "Washington": "1159090",
  "West Virginia": "368729",
  "Wisconsin": "800155",
  "Wyoming": "67247"
 },
 "2000": {
  "Alabama": "592836",
  "Alaska": "275657",
  "Arizona": "1230937",
  "Arkansas": "710687",
  "California": "7806202",
  "Colorado": "709750",
  "Connecticut": "587627",
  "Delaware": "219466",
  "District of Columbia": "293166",
  "Florida": "2684787",
  "Georgia": "1741674",
  "Hawaii": "189779",
  "Idaho": "212413",
  "Illinois": "2077545",
  "Indiana": "1100228",
  "Iowa": "527945",
  "Kansas": "420785",
  "Kentucky": "1187906",
  "Louisiana": "1092198",
  "Maine": "471586",
  "Maryland": "1191485",
  "Massachusetts": "1479298",
  "Michigan": "1627177",
  "Minnesota": "1013042",
  "Mississippi": "677372",
  "Missouri": "1269128",
  "Montana": "174467",
  "Nebraska": "362513",
  "Nevada": "269322",
  "New Hampshire": "233744",
  "New Jersey": "1705915",
  "New Mexico": "602950",
  "New York": "7264995",
  "North Carolina": "1917257",
  "North Dakota": "98151",
  "Ohio": "1855921",
  "Oklahoma": "624144",
  "Oregon": "762162",
  "Pennsylvania": "3731819",
  "Rhode Island": "287416",
  "South Carolina": "925262",
  "South Dakota": "148329",
  "Tennessee": "2120488",
  "Texas": "4380275",
  "Utah": "295324",
  "Vermont": "218845",
  "Virginia": "880856",
  "Washington": "1559194",
  "West Virginia": "395727",
  "Wisconsin": "854838",
  "Wyoming": "73529"
 },
 "2001": {
  "Alabama": "797087",
  "Alaska": "334414",
  "Arizona": "1495353",
  "Arkansas": "862637",
  "California": "8639802",
  "Colorado": "793289",
  "Connecticut": "448360",
  "Delaware": "242472",
  "District of Columbia": "340435",
  "Florida": "3158652",
  "Georgia": "2084488",
  "Hawaii": "182931",
  "Idaho": "265048",
  "Illinois": "2272754",
  "Indiana": "1277864",
  "Iowa": "547703",
  "Kansas": "537957",
  "Kentucky": "1281288",
  "Louisiana": "1393483",
  "Maine": "533823",
  "Maryland": "1274503",
  "Massachusetts": "1490233",
  "Michigan": "1944597",
  "Minnesota": "1210247",
  "Mississippi": "897754",
  "Missouri": "1576696",
  "Montana": "200636",
  "Nebraska": "417136",
  "Nevada": "293435",
  "New Hampshire": "276978",
  "New Jersey": "2062439",
  "New Mexico": "725432",
  "New York": "7190552",
  "North Carolina": "2154700",
  "North Dakota": "89693",
  "Ohio": "2154613",
  "Oklahoma": "776283",
  "Oregon": "934920",
  "Pennsylvania": "3929703",
  "Rhode Island": "389714",
  "South Carolina": "1016670",
  "South Dakota": "176367",
  "Tennessee": "1791019",
  "Texas": "5281740",
  "Utah": "333994",
  "Vermont": "249701",
  "Virginia": "994460",
  "Washington": "1702710",
  "West Virginia": "491577",
  "Wisconsin": "1111391",
  "Wyoming": "89498"
 },
 "2002": {
  "Alabama": "1077113",
  "Alaska": "390702",
  "Arizona": "2114369",
  "Arkansas": "1071055",
  "California": "9798618",
  "Colorado": "842266",
  "Connecticut": "704110",
  "Delaware": "228447",
  "District of Columbia": "358833",
  "Florida": "3577922",
  "Georgia": "2658044",
  "Hawaii": "212841",
  "Idaho": "296470",
  "Illinois": "2433415",
  "Indiana": "1452256",
  "Iowa": "851163",
  "Kansas": "617697",
  "Kentucky": "1493149",
  "Louisiana": "1791438",
  "Maine": "568860",
  "Maryland": "1399241",
  "Massachusetts": "1811266",
  "Michigan": "2067580",
  "Minnesota": "1605071",
  "Mississippi": "1098935",
  "Missouri": "1764948",
  "Montana": "231873",
  "Nebraska": "460443",
  "Nevada": "342529",
  "New Hampshire": "326529",
  "New Jersey": "2385651",
  "New Mexico": "829169",
  "New York": "8287181",
  "North Carolina": "2495240",
  "North Dakota": "101368",
  "Ohio": "2434667",
  "Oklahoma": "872017",
  "Oregon": "872422",
  "Pennsylvania": "4418423",
  "Rhode Island": "477005",
  "South Carolina": "1115218",
  "South Dakota": "231707",
  "Tennessee": "1593835",
  "Texas": "6984070",
  "Utah": "387971",
  "Vermont": "285828",
  "Virginia": "1289903",
  "Washington": "1326155",
  "West Virginia": "511938",
  "Wisconsin": "1140803",
  "Wyoming": "103851"
 },
 "2003": {
  "Alabama": "1254433",
  "Alaska": "463475",
  "Arizona": "2552053",
  "Arkansas": "1085642",
  "California": "10919243",
  "Colorado": "922728",
  "Connecticut": "730037",
  "Delaware": "282096",
  "District of Columbia": "351689",
  "Florida": "4010396",
  "Georgia": "2849267",
  "Hawaii": "239626",
  "Idaho": "324461",
  "Illinois": "2403654",
  "Indiana": "1404795",
  "Iowa": "709789",
  "Kansas": "630720",
  "Kentucky": "1443810",
  "Louisiana": "1472361",
  "Maine": "693756",
  "Maryland": "1575737",
  "Massachusetts": "1712898",
  "Michigan": "2285727",
  "Minnesota": "1757847",
  "Mississippi": "1105745",
  "Missouri": "1768849",
  "Montana": "202693",
  "Nebraska": "475064",
  "Nevada": "442325",
  "New Hampshire": "300224",
  "New Jersey": "2482842",
  "New Mexico": "920946",
  "New York": "8735758",
  "North Carolina": "2709201",
  "North Dakota": "106830",
  "Ohio": "2529633",
  "Oklahoma": "963367",
  "Oregon": "953702",
  "Pennsylvania": "4675952",
  "Rhode Island": "493795",
  "South Carolina": "1196079",
  "South Dakota": "220626",
  "Tennessee": "1563968",
  "Texas": "7765656",
  "Utah": "416900",
  "Vermont": "290334",
  "Virginia": "1174128",
  "Washington": "1307763",
  "West Virginia": "548719",
  "Wisconsin": "1255456",
  "Wyoming": "133965"
 },
 "2004": {
  "Alabama": "1196914",
  "Alaska": "482070",
  "Arizona": "3017641",
  "Arkansas": "1236307",
  "California": "10457587",
  "Colorado": "934242",
  "Connecticut": "792699",
  "Delaware": "287941",
  "District of Columbia": "336516",
  "Florida": "4381162",
  "Georgia": "2957284",
  "Hawaii": "271629",
  "Idaho": "380502",
  "Illinois": "2733711",
  "Indiana": "1617937",
  "Iowa": "738617",
  "Kansas": "693020",
  "Kentucky": "1554483",
  "Louisiana": "1737049",
  "Maine": "741344",
  "Maryland": "1645848",
  "Massachusetts": "2573870",
  "Michigan": "2752252",
  "Minnesota": "2043322",
  "Mississippi": "1077439",
  "Missouri": "1851025",
  "Montana": "258401",
  "Nebraska": "486846",
  "Nevada": "438453",
  "New Hampshire": "373691",
  "New Jersey": "2201901",
  "New Mexico": "963848",
  "New York": "8290301",
  "North Carolina": "3006135",
  "North Dakota": "113867",
  "Ohio": "2914646",
  "Oklahoma": "1041659",
  "Oregon": "906945",
  "Pennsylvania": "4867544",
  "Rhode Island": "615153",
  "South Carolina": "1196541",
  "South Dakota": "230648",
  "Tennessee": "1761219",
  "Texas": "8141764",
  "Utah": "442910",
  "Vermont": "302614",
  "Virginia": "1273338",
  "Washington": "1467479",
  "West Virginia": "508993",
  "Wisconsin": "1088401",
  "Wyoming": "148977"
 },
 "2005": {
  "Alabama": "1209594",
  "Alaska": "500077",
  "Arizona": "3199876",
  "Arkansas": "1287643",
  "California": "11051756",
  "Colorado": "933451",
  "Connecticut": "823488",
  "Delaware": "320786",
  "District of Columbia": "401026",
  "Florida": "4301265",
  "Georgia": "3114378",
  "Hawaii": "330299",
  "Idaho": "409979",
  "Illinois": "2969159",
  "Indiana": "1553694",
  "Iowa": "771037",
  "Kansas": "731026",
  "Kentucky": "1563989",
  "Louisiana": "1653786",
  "Maine": "806291",
  "Maryland": "1742656",
  "Massachusetts": "2684318",
  "Michigan": "2498096",
  "Minnesota": "1867172",
  "Mississippi": "1096111",
  "Missouri": "1917584",
  "Montana": "266474",
  "Nebraska": "491314",
  "Nevada": "467235",
  "New Hampshire": "378376",
  "New Jersey": "1991968",
  "New Mexico": "961465",
  "New York": "8619461",
  "North Carolina": "3276039",
  "North Dakota": "115003",
  "Ohio": "2821569",
  "Oklahoma": "1131674",
  "Oregon": "983619",
  "Pennsylvania": "5378552",
  "Rhode Island": "609264",
  "South Carolina": "1270840",
  "South Dakota": "246930",
  "Tennessee": "1814466",
  "Texas": "8544244",
  "Utah": "437255",
  "Vermont": "313933",
  "Virginia": "1469616",
  "Washington": "1592061",
  "West Virginia": "577085",
  "Wisconsin": "1125628",
  "Wyoming": "172013"
 },
 "2006": {
  "Alabama": "1350494",
  "Alaska": "474209",
  "Arizona": "3921606",
  "Arkansas": "1339611",
  "California": "11900671",
  "Colorado": "1027158",
  "Connecticut": "839461",
  "Delaware": "349958",
  "District of Columbia": "375349",
  "Florida": "4272764",
  "Georgia": "2941621",
  "Hawaii": "329571",
  "Idaho": "431247",
  "Illinois": "2989909",
  "Indiana": "1847537",
  "Iowa": "831994",
  "Kansas": "824275",
  "Kentucky": "1586268",
  "Louisiana": "1476704",
  "Maine": "692528",
  "Maryland": "1754458",
  "Massachusetts": "3049432",
  "Michigan": "2551509",
  "Minnesota": "1782550",
  "Mississippi": "1145511",
  "Missouri": "2114246",
  "Montana": "287967",
  "Nebraska": "563312",
  "Nevada": "482952",
  "New Hampshire": "372258",
  "New Jersey": "2516924",
  "New Mexico": "1015852",
  "New York": "8743334",
  "North Carolina": "3435018",
  "North Dakota": "123293",
  "Ohio": "2999321",
  "Oklahoma": "1222083",
  "Oregon": "1081650",
  "Pennsylvania": "5977375",
  "Rhode Island": "621011",
  "South Carolina": "1283830",
  "South Dakota": "249205",
  "Tennessee": "1948373",
  "Texas": "9243978",
  "Utah": "466650",
  "Vermont": "351489",
  "Virginia": "1683261",
  "Washington": "1640205",
  "West Virginia": "619128",
  "Wisconsin": "1151681",
  "Wyoming": "177352"
 },
 "2007": {
  "Alabama": "1478251",
  "Alaska": "460099",
  "Arizona": "4176444",
  "Arkansas": "1381887",
  "California": "11849273",
  "Colorado": "1006815",
  "Connecticut": "910831",
  "Delaware": "363754",
  "District of Columbia": "369583",
  "Florida": "4499873",
  "Georgia": "3374591",
  "Hawaii": "329426",
  "Idaho": "480286",
  "Illinois": "4241894",
  "Indiana": "1662386",
  "Iowa": "801754",
  "Kansas": "852169",
  "Kentucky": "1736139",
  "Louisiana": "1469260",
  "Maine": "674849",
  "Maryland": "1882486",
  "Massachusetts": "2976834",
  "Michigan": "2870666",
  "Minnesota": "2056043",
  "Mississippi": "1182721",
  "Missouri": "2223193",
  "Montana": "289677",
  "Nebraska": "563545",
  "Nevada": "523995",
  "New Hampshire": "403828",
  "New Jersey": "2640433",
  "New Mexico": "1047475",
  "New York": "8591757",
  "North Carolina": "4063344",
  "North Dakota": "120130",
  "Ohio": "3263669",
  "Oklahoma": "1401808",
  "Oregon": "1044726",
  "Pennsylvania": "6162901",
  "Rhode Island": "627044",
  "South Carolina": "1273040",
  "South Dakota": "250322",
  "Tennessee": "2308399",
  "Texas": "10727071",
  "Utah": "451685",
  "Vermont": "390235",
  "Virginia": "1826194",
  "Washington": "1689533",
  "West Virginia": "631149",
  "Wisconsin": "1219005",
  "Wyoming": "168699"
 },
 "2008": {
  "Alabama": "1707418",
  "Alaska": "410904",
  "Arizona": "3498300",
  "Arkansas": "1479148",
  "California": "12895387",
  "Colorado": "1107695",
  "Connecticut": "594011",
  "Delaware": "393156",
  "District of Columbia": "340914",
  "Florida": "4913285",
  "Georgia": "3240568",
  "Hawaii": "351363",
  "Idaho": "504214",
  "Illinois": "3643456",
  "Indiana": "1910899",
  "Iowa": "890832",
  "Kansas": "788347",
  "Kentucky": "1835721",
  "Louisiana": "1938513",
  "Maine": "727824",
  "Maryland": "1894524",
  "Massachusetts": "3092574",
  "Michigan": "2797702",
  "Minnesota": "2274488",
  "Mississippi": "1543037",
  "Missouri": "2395314",
  "Montana": "307903",
  "Nebraska": "585893",
  "Nevada": "571802",
  "New Hampshire": "411034",
  "New Jersey": "2749517",
  "New Mexico": "1304561",
  "New York": "8610585",
  "North Carolina": "4036960",
  "North Dakota": "132534",
  "Ohio": "3048756",
  "Oklahoma": "1439978",
  "Oregon": "1132320",
  "Pennsylvania": "6022484",
  "Rhode Island": "640067",
  "South Carolina": "1441961",
  "South Dakota": "268586",
  "Tennessee": "2420677",
  "Texas": "11880440",
  "Utah": "509003",
  "Vermont": "380150",
  "Virginia": "1967841",
  "Washington": "1838118",
  "West Virginia": "613291",
  "Wisconsin": "1090340",
  "Wyoming": "191787"
 },
 "2009": {
  "Alabama": "1999539",
  "Alaska": "482274",
  "Arizona": "3837541",
  "Arkansas": "1499049",
  "California": "13786973",
  "Colorado": "1320570",
  "Connecticut": "1014224",
  "Delaware": "428542",
  "District of Columbia": "361756",
  "Florida": "5269377",
  "Georgia": "3195529",
  "Hawaii": "355178",
  "Idaho": "552335",
  "Illinois": "4339391",
  "Indiana": "1735464",
  "Iowa": "974361",
  "Kansas": "889351",
  "Kentucky": "2168153",
  "Louisiana": "2280905",
  "Maine": "723285",
  "Maryland": "2107772",
  "Massachusetts": "3243225",
  "Michigan": "3262784",
  "Minnesota": "2272377",
  "Mississippi": "1632791",
  "Missouri": "2628344",
  "Montana": "349583",
  "Nebraska": "588353",
  "Nevada": "620989",
  "New Hampshire": "416027",
  "New Jersey": "3185892",
  "New Mexico": "2010419",
  "New York": "9034893",
  "North Carolina": "4538800",
  "North Dakota": "140570",
  "Ohio": "3450082",
  "Oklahoma": "1652463",
  "Oregon": "1214921",
  "Pennsylvania": "6419235",
  "Rhode Island": "688461",
  "South Carolina": "1673933",
  "South Dakota": "293227",
  "Tennessee": "2486077",
  "Texas": "13176185",
  "Utah": "632995",
  "Vermont": "415624",
  "Virginia": "2183304",
  "Washington": "2079179",
  "West Virginia": "716090",
  "Wisconsin": "1428600",
  "Wyoming": "195723"
 },
 "2010": {
  "Alabama": "2379098",
  "Alaska": "539143",
  "Arizona": "3641389",
  "Arkansas": "1717950",
  "California": "14607708",
  "Colorado": "1576669",
  "Connecticut": "1233999",
  "Delaware": "452554",
  "District of Columbia": "373222",
  "Florida": "6286738",
  "Georgia": "3146624",
  "Hawaii": "374736",
  "Idaho": "601856",
  "Illinois": "5434568",
  "Indiana": "1687474",
  "Iowa": "1086282",
  "Kansas": "922970",
  "Kentucky": "2310888",
  "Louisiana": "2596656",
  "Maine": "587204",
  "Maryland": "2332108",
  "Massachusetts": "3014049",
  "Michigan": "3729627",
  "Minnesota": "2247305",
  "Mississippi": "1742948",
  "Missouri": "2740872",
  "Montana": "376730",
  "Nebraska": "589806",
  "Nevada": "712063",
  "New Hampshire": "400274",
  "New Jersey": "3782877",
  "New Mexico": "2462289",
  "New York": "9964857",
  "North Carolina": "4407743",
  "North Dakota": "167798",
  "Ohio": "3684654",
  "Oklahoma": "1747538",
  "Oregon": "1259424",
  "Pennsylvania": "7070386",
  "Rhode Island": "812260",
  "South Carolina": "1941304",
  "South Dakota": "325352",
  "Tennessee": "2863641",
  "Texas": "15429041",
  "Utah": "758460",
  "Vermont": "433538",
  "Virginia": "2534823",
  "Washington": "2385928",
  "West Virginia": "814915",
  "Wisconsin": "1417579",
  "Wyoming": "190708"
 },
 "2011": {
  "Alabama": "2162925",
  "Alaska": "546794",
  "Arizona": "3309167",
  "Arkansas": "1801957",
  "California": "19693994",
  "Colorado": "1625283",
  "Connecticut": "1166244",
  "Delaware": "479825",
  "District of Columbia": "442349",
  "Florida": "6544119",
  "Georgia": "3591001",
  "Hawaii": "386265",
  "Idaho": "650428",
  "Illinois": "4290360",
  "Indiana": "1943498",
  "Iowa": "1148313",
  "Kansas": "995275",
  "Kentucky": "2262237",
  "Louisiana": "2456360",
  "Maine": "604023",
  "Maryland": "2372791",
  "Massachusetts": "3482449",
  "Michigan": "3677366",
  "Minnesota": "2395177",
  "Mississippi": "1844005",
  "Missouri": "2507064",
  "Montana": "393602",
  "Nebraska": "544089",
  "Nevada": "725299",
  "New Hampshire": "427514",
  "New Jersey": "4015947",
  "New Mexico": "2201402",
  "New York": "9968522",
  "North Carolina": "4258753",
  "North Dakota": "174880",
  "Ohio": "3817522",
  "Oklahoma": "1774136",
  "Oregon": "1319509",
  "Pennsylvania": "7526281",
  "Rhode Island": "825732",
  "South Carolina": "1821098",
  "South Dakota": "318507",
  "Tennessee": "2595980",
  "Texas": "16167781",
  "Utah": "758141",
  "Vermont": "553070",
  "Virginia": "2583306",
  "Washington": "2499558",
  "West Virginia": "826559",
  "Wisconsin": "1441309",
  "Wyoming": "172402"
 },
 "2012": {
  "Alabama": "2154499",
  "Alaska": "549171",
  "Arizona": "3171855",
  "Arkansas": "1928234",
  "California": "16617703",
  "Colorado": "1744886",
  "Connecticut": "1281195",
  "Delaware": "483791",
  "District of Columbia": "416179",
  "Florida": "6162145",
  "Georgia": "2986661",
  "Hawaii": "353753",
  "Idaho": "578713",
  "Illinois": "4006205",
  "Indiana": "1983282",
  "Iowa": "1154809",
  "Kansas": "1082954",
  "Kentucky": "2254816",
  "Louisiana": "2496331",
  "Maine": "561490",
  "Maryland": "2336354",
  "Massachusetts": "3156401",
  "Michigan": "4068946",
  "Minnesota": "2168635",
  "Mississippi": "1765789",
  "Missouri": "2466626",
  "Montana": "408332",
  "Nebraska": "505721",
  "Nevada": "773468",
  "New Hampshire": "327291",
  "New Jersey": "3640540",
  "New Mexico": "1942921",
  "New York": "9925578",
  "North Carolina": "4795717",
  "North Dakota": "185293",
  "Ohio": "3911871",
  "Oklahoma": "1888423",
  "Oregon": "1383378",
  "Pennsylvania": "7130885",
  "Rhode Island": "623130",
  "South Carolina": "1674505",
  "South Dakota": "288416",
  "Tennessee": "2333750",
  "Texas": "15067545",
  "Utah": "792782",
  "Vermont": "642437",
  "Virginia": "2337639",
  "Washington": "2499886",
  "West Virginia": "764768",
  "Wisconsin": "1365869",
  "Wyoming": "153157"
 },
 "2013": {
  "Alabama": "2218549",
  "Alaska": "596601",
  "Arizona": "3544018",
  "Arkansas": "2069898",
  "California": "22832856",
  "Colorado": "1953378",
  "Connecticut": "1223203",
  "Delaware": "507459",
  "District of Columbia": "459673",
  "Florida": "6625330",
  "Georgia": "3552390",
  "Hawaii": "390439",
  "Idaho": "698256",
  "Illinois": "5028043",
  "Indiana": "2018495",
  "Iowa": "1252020",
  "Kansas": "1469677",
  "Kentucky": "2330664",
  "Louisiana": "2332088",
  "Maine": "714458",
  "Maryland": "2437258",
  "Massachusetts": "3401929",
  "Michigan": "3983948",
  "Minnesota": "2306279",
  "Mississippi": "1863106",
  "Missouri": "2696870",
  "Montana": "461349",
  "Nebraska": "559993",
  "Nevada": "865072",
  "New Hampshire": "377656",
  "New Jersey": "3744981",
  "New Mexico": "1957238",
  "New York": "10522390",
  "North Carolina": "4978524",
  "North Dakota": "208656",
  "Ohio": "4129788",
  "Oklahoma": "1968367",
  "Oregon": "1574154",
  "Pennsylvania": "7649963",
  "Rhode Island": "754253",
  "South Carolina": "1815631",
  "South Dakota": "303705",
  "Tennessee": "2548247",
  "Texas": "15602433",
  "Utah": "926179",
  "Vermont": "738732",
  "Virginia": "2533162",
  "Washington": "2726133",
  "West Virginia": "862363",
  "Wisconsin": "1518403",
  "Wyoming": "176956"
 },
 "2014": {
  "Alabama": "2329033",
  "Alaska": "617269",
  "Arizona": "3881737",
  "Arkansas": "2403553",
  "California": "21919302",
  "Colorado": "1992525",
  "Connecticut": "1340431",
  "Delaware": "552657",
  "District of Columbia": "473493",
  "Florida": "7077148",
  "Georgia": "3872130",
  "Hawaii": "458039",
  "Idaho": "659254",
  "Illinois": "5283333",
  "Indiana": "2253455",
  "Iowa": "1262933",
  "Kansas": "1376860",
  "Kentucky": "2671763",
  "Louisiana": "2414339",
  "Maine": "572523",
  "Maryland": "2844602",
  "Massachusetts": "3434889",
  "Michigan": "4483893",
  "Minnesota": "2709678",
  "Mississippi": "1925290",
  "Missouri": "2518828",
  "Montana": "508236",
  "Nebraska": "564209",
  "Nevada": "1186852",
  "New Hampshire": "376522",
  "New Jersey": "3460763",
  "New Mexico": "2370879",
  "New York": "11030101",
  "North Carolina": "4928715",
  "North Dakota": "117490",
  "Ohio": "5045691",
  "Oklahoma": "2045138",
  "Oregon": "1921890",
  "Pennsylvania": "8151167",
  "Rhode Island": "806782",
  "South Carolina": "2093205",
  "South Dakota": "305268",
  "Tennessee": "2976156",
  "Texas": "17286782",
  "Utah": "907261",
  "Vermont": "745927",
  "Virginia": "2621358",
  "Washington": "1827785",
  "West Virginia": "889761",
  "Wisconsin": "2368947",
  "Wyoming": "172507"
 },
 "2015": {
  "Alabama": "2234322",
  "Alaska": "553473",
  "Arizona": "3936078",
  "Arkansas": "2781097",
  "California": "21759578",
  "Colorado": "2194569",
  "Connecticut": "1102000",
  "Delaware": "562971",
  "District of Columbia": "439235",
  "Florida": "7139185",
  "Georgia": "3717640",
  "Hawaii": "406653",
  "Idaho": "638685",
  "Illinois": "4417766",
  "Indiana": "1934781",
  "Iowa": "1333333",
  "Kansas": "1607047",
  "Kentucky": "3198796",
  "Louisiana": "2493451",
  "Maine": "563241",
  "Maryland": "2679037",
  "Massachusetts": "3178619",
  "Michigan": "4403567",
  "Minnesota": "2502399",
  "Mississippi": "1996448",
  "Missouri": "2642453",
  "Montana": "463314",
  "Nebraska": "535779",
  "Nevada": "1172899",
  "New Hampshire": "420350",
  "New Jersey": "3388884",
  "New Mexico": "2339255",
  "New York": "11730959",
  "North Carolina": "5134785",
  "North Dakota": "227079",
  "Ohio": "4396952",
  "Oklahoma": "1895996",
  "Oregon": "1741698",
  "Pennsylvania": "6745394",
  "Rhode Island": "795661",
  "South Carolina": "2038937",
  "South Dakota": "285759",
  "Tennessee": "2654693",
  "Texas": "17921042",
  "Utah": "960634",
  "Vermont": "773175",
  "Virginia": "2575439",
  "Washington": "3229622",
  "West Virginia": "832235",
  "Wisconsin": "1641414",
  "Wyoming": "156879"
 },
 "2016": {
  "Alabama": "2288559",
  "Alaska": "633218",
  "Arizona": "3957936",
  "Arkansas": "2804363",
  "California": "21432466",
  "Colorado": "2244358",
  "Connecticut": "1099090",
  "Delaware": "542368",
  "District of Columbia": "503708",
  "Florida": "7243424",
  "Georgia": "3662056",
  "Hawaii": "434587",
  "Idaho": "640189",
  "Illinois": "4878731",
  "Indiana": "1998804",
  "Iowa": "1350452",
  "Kansas": "1712379",
  "Kentucky": "3251869",
  "Louisiana": "2695992",
  "Maine": "560738",
  "Maryland": "2703458",
  "Massachusetts": "3705448",
  "Michigan": "4370880",
  "Minnesota": "2545726",
  "Mississippi": "2116938",
  "Missouri": "2675926",
  "Montana": "483991",
  "Nebraska": "547983",
  "Nevada": "1164740",
  "New Hampshire": "441747",
  "New Jersey": "3372715",
  "New Mexico": "2449713",
  "New York": "12160938",
  "North Carolina": "4716117",
  "North Dakota": "223667",
  "Ohio": "4203160",
  "Oklahoma": "1851090",
  "Oregon": "1805149",
  "Pennsylvania": "7311335",
  "Rhode Island": "764809",
  "South Carolina": "2061571",
  "South Dakota": "293941",
  "Tennessee": "2990718",
  "Texas": "20010150",
  "Utah": "904106",
  "Vermont": "773328",
  "Virginia": "2692382",
  "Washington": "3452744",
  "West Virginia": "788600",
  "Wisconsin": "1594035",
  "Wyoming": "159781"
 }
}